[
 {
  "name": "\u5c40\u5916\u7cfb\u7edf", 
  "key": "aFZ3IXe-Ee6nOjDQQunfyY", 
  "group": [
   {
    "__tuple__": true, 
    "items": [
     "5045b209-ac7e-4d81-920f-20d319f60e84", 
     "\u6d1b\u9633\u5bab\u914d\u7f6e\u8868"
    ]
   }, 
   {
    "__tuple__": true, 
    "items": [
     "e49e8860-5624-4fa9-98b5-2e3146b088c2", 
     "\u519b\u8854\u5347\u7ea7\u6d88\u8017\u8868"
    ]
   }, 
   {
    "__tuple__": true, 
    "items": [
     "3b262ea3-7049-44f5-a8bd-7078bac49208", 
     "\u5175\u7b26\u76f8\u5173\u8d44\u6e90\u8868"
    ]
   }, 
   {
    "__tuple__": true, 
    "items": [
     "360684f3-478c-419a-8b7f-3fbcecc895c6", 
     "\u5175\u7b26\u526f\u5c5e\u6027\u8868"
    ]
   }, 
   {
    "__tuple__": true, 
    "items": [
     "335e3206-490b-4198-a2cd-8b163dea3916", 
     "\u5175\u7b26\u5957\u88c5\u914d\u7f6e\u8868"
    ]
   }, 
   {
    "__tuple__": true, 
    "items": [
     "5e52bffc-d309-4f2a-b501-9e507b28d7b7", 
     "\u7ec3\u5175\u573a\u9776\u5b50\u4f4d\u7f6e"
    ]
   }, 
   {
    "__tuple__": true, 
    "items": [
     "c276ad61-d08e-4ec1-acde-e6a87239f9e9", 
     "\u7ec3\u5175\u573a\u5956\u52b1\u914d\u7f6e\u8868"
    ]
   }, 
   {
    "__tuple__": true, 
    "items": [
     "63276bac-6b73-4a3d-aa6d-c41ae0daee9c", 
     "\u5185\u52a1\u90e8\u914d\u7f6e\u8868"
    ]
   }, 
   {
    "__tuple__": true, 
    "items": [
     "68d2f6bd-4016-4c28-bd81-5a957984433b", 
     "\u9a81\u9a91\u4ee4\u914d\u7f6e\u8868"
    ]
   }, 
   {
    "__tuple__": true, 
    "items": [
     "c01a9731-c00c-4c46-bb08-4b39a269fbad", 
     "\u94dc\u96c0\u53f0\u914d\u7f6e\u8868"
    ]
   }, 
   {
    "__tuple__": true, 
    "items": [
     "590754c7-f214-4204-852e-8236614138ff", 
     "\u9f99\u864e\u699c\u5f81\u6218\u4e09\u56fd\u901f\u901a"
    ]
   }, 
   {
    "__tuple__": true, 
    "items": [
     "27779b60-9837-4232-8f89-0af824a09f6d", 
     "\u6210\u5c31\u914d\u7f6e\u88682"
    ]
   }, 
   {
    "__tuple__": true, 
    "items": [
     "05b3815e-86ae-440d-ab43-e633e5ce07cb", 
     "\u6210\u5c31\u914d\u7f6e\u88681"
    ]
   }, 
   {
    "__tuple__": true, 
    "items": [
     "50269307-9c6c-4053-96c7-44d09e8da586", 
     "\u5c40\u5916\u6b66\u5c06\u914d\u7f6e\u8868"
    ]
   }, 
   {
    "__tuple__": true, 
    "items": [
     "8c6ab752-c0b7-4225-8f3a-b63cc623dad0", 
     "\u5c40\u5916\u88c5\u5907\uff08\u795e\u5668\uff09\u914d\u7f6e\u8868"
    ]
   }
  ]
 }, 
 {
  "name": "\u5b58\u6863", 
  "key": "2uSiT3MNEe6LJDDQQunfyQ", 
  "group": [
   {
    "__tuple__": true, 
    "items": [
     "b47087c1-8974-4bf8-8ff4-b7255e7f3ce1", 
     "\u5b58\u6863\u4fe1\u606f\u603b\u8868"
    ]
   }, 
   {
    "__tuple__": true, 
    "items": [
     "7001566d-faa7-45e2-9d7a-8c802019c571", 
     "\u6731\u96c0\u5175\u7b26\u4ed3\u5e93"
    ]
   }, 
   {
    "__tuple__": true, 
    "items": [
     "b58a1ba2-d2f8-4f16-b894-4c13ff4ac96d", 
     "\u7384\u6b66\u5175\u7b26\u4ed3\u5e93"
    ]
   }, 
   {
    "__tuple__": true, 
    "items": [
     "9c8f9d8e-8f35-46b7-9b46-71de81cca6e5", 
     "\u9752\u9f99\u5175\u7b26\u4ed3\u5e93"
    ]
   }, 
   {
    "__tuple__": true, 
    "items": [
     "3b8c4516-87ac-401a-bdd1-a9c68e55e551", 
     "\u767d\u864e\u5175\u7b26\u4ed3\u5e93"
    ]
   }, 
   {
    "__tuple__": true, 
    "items": [
     "ac9b0072-816f-44d6-bb2b-4d173419558a", 
     "\u5c40\u5916\u6b66\u5c06\u4fe1\u606f\u8868"
    ]
   }, 
   {
    "__tuple__": true, 
    "items": [
     "e27aebf2-b54a-479a-934a-81c9a59a1aa5", 
     "\u5c40\u5916\u88c5\u5907\u4fe1\u606f\u8868"
    ]
   }, 
   {
    "__tuple__": true, 
    "items": [
     "af0fe1da-8730-450d-ad33-425a2fb15e33", 
     "\u6d1b\u9633\u5bab\u5b58\u6863\u8868"
    ]
   }, 
   {
    "__tuple__": true, 
    "items": [
     "d787a630-7762-44f6-acef-11e9cc0458d8", 
     "\u6210\u5c31\u5b58\u6863\u88682"
    ]
   }, 
   {
    "__tuple__": true, 
    "items": [
     "a142239d-8819-4774-a138-b2e97d89df03", 
     "\u6210\u5c31\u5b58\u6863\u88681"
    ]
   }, 
   {
    "__tuple__": true, 
    "items": [
     "50c22c05-09ed-44a4-bc05-44e5629ac76b", 
     "\u5168\u4f53\u5c5e\u6027\u5b58\u6863"
    ]
   }, 
   {
    "__tuple__": true, 
    "items": [
     "3b0d9c80-d16c-406b-8659-7d34cda9c8c5", 
     "\u5185\u52a1\u90e8\u5b58\u6863\u8868"
    ]
   }, 
   {
    "__tuple__": true, 
    "items": [
     "e620e081-db82-4e56-9f58-673265826ef7", 
     "\u94dc\u96c0\u53f0\u5b58\u6863\u8868"
    ]
   }, 
   {
    "__tuple__": true, 
    "items": [
     "e8659e19-3c5d-42cb-849f-ea91607279bf", 
     "\u9a81\u9a91\u4ee4\u5b58\u6863\u8868"
    ]
   }, 
   {
    "__tuple__": true, 
    "items": [
     "a6f7b260-7688-469c-8b8c-6beb7dd6e3bc", 
     "\u5f81\u6218\u4e09\u56fd\u5173\u5361\u5b58\u6863\u8868"
    ]
   }
  ]
 }, 
 {
  "name": "\u5c40\u5185\u6570\u636e", 
  "key": "Q4Qc0XeYEe6sDjDQQunfyf", 
  "group": [
   {
    "__tuple__": true, 
    "items": [
     "8599df08-3a6f-4461-902c-74ca81a4bc2f", 
     "\u5c40\u5185\u6b66\u5c06\u8868"
    ]
   }, 
   {
    "__tuple__": true, 
    "items": [
     "497d943e-be4d-4dbb-8108-03d07bcafc7f", 
     "\u5c40\u5185\u88c5\u5907\u8868"
    ]
   }
  ]
 }, 
 {
  "name": "\u5c40\u5185\u914d\u7f6e", 
  "key": "ZEJgLneYEe6ppDDQQunfyf", 
  "group": [
   {
    "__tuple__": true, 
    "items": [
     "0b671a54-6313-48da-bbbe-6553f541c79a", 
     "\u7b49\u7ea7\u8868"
    ]
   }, 
   {
    "__tuple__": true, 
    "items": [
     "f0baf6e1-5ed8-4881-bbce-69b807637be0", 
     "\u5347\u7ea7\u5956\u52b1\u6743\u91cd\u8868"
    ]
   }, 
   {
    "__tuple__": true, 
    "items": [
     "4225971d-a063-4477-99d5-ac7b48c881dc", 
     "\u9053\u5177\u914d\u7f6e\u8868"
    ]
   }
  ]
 }, 
 {
  "__tuple__": true, 
  "items": [
   "f9d00e30-ccc8-4ad0-abbe-63ac6283b63f", 
   "\u7cfb\u7edf\u914d\u7f6e\u603b\u8868"
  ]
 }, 
 {
  "__tuple__": true, 
  "items": [
   "e69b00ad-915d-4344-86e3-c2d0a3353b77", 
   "\u88c5\u5907\u914d\u7f6e\u8868"
  ]
 }, 
 {
  "__tuple__": true, 
  "items": [
   "a2d3b99a-44eb-4226-9666-7e3e897ddf59", 
   "\u6b66\u5c06\u914d\u7f6e\u8868"
  ]
 }, 
 {
  "name": "\u5173\u5361", 
  "key": "IjlQ4XeYEe6n-DDQQunfyV", 
  "group": [
   {
    "name": "\u5b98\u6e21\u4e4b\u6218", 
    "key": "4CISQInWEe6YJPh1pC-oXI", 
    "group": [
     {
      "__tuple__": true, 
      "items": [
       "8d5dc9ac-d229-45da-9d44-525c74a34f31", 
       "\u5b98\u6e21\u4e4b\u6218\u57fa\u672c\u51fa\u602a\u8868"
      ]
     }, 
     {
      "__tuple__": true, 
      "items": [
       "13ffc428-12a8-4598-896d-b575e1ea5c7d", 
       "\u5b98\u6e21\u4e4b\u6218\u5173\u5361\u7279\u6b8a\u4e8b\u4ef6"
      ]
     }, 
     {
      "__tuple__": true, 
      "items": [
       "cd1db223-79e6-4fa4-90a8-b9eaaf091e0f", 
       "\u5b98\u6e21\u4e4b\u6218\u654c\u4eba\u914d\u7f6e\u8868"
      ]
     }
    ]
   }, 
   {
    "name": "\u9ec4\u5dfe\u4e4b\u4e71", 
    "key": "ztemMInWEe6MZfh1pC-oXP", 
    "group": [
     {
      "__tuple__": true, 
      "items": [
       "90fdaf95-b41a-4f3d-94f1-13ae679cada2", 
       "\u9ec4\u5dfe\u4e4b\u4e71\u5173\u5361\u7279\u6b8a\u4e8b\u4ef6"
      ]
     }, 
     {
      "__tuple__": true, 
      "items": [
       "fe476fb5-bec8-46cc-af96-45340b44bfb3", 
       "\u9ec4\u5dfe\u4e4b\u4e71\u57fa\u672c\u51fa\u602a\u8868"
      ]
     }, 
     {
      "__tuple__": true, 
      "items": [
       "5936887f-32fe-46d1-8b00-5d96b3392c2e", 
       "\u9ec4\u5dfe\u4e4b\u4e71\u5956\u52b1\u65d7"
      ]
     }, 
     {
      "__tuple__": true, 
      "items": [
       "e399e62b-e670-4b07-89a9-58255fbd00fb", 
       "\u9ec4\u5dfe\u4e4b\u4e71\u654c\u4eba\u914d\u7f6e\u8868"
      ]
     }
    ]
   }, 
   {
    "__tuple__": true, 
    "items": [
     "d756548d-5d31-4e0e-bf39-d3fb17b223c2", 
     "\u5f81\u6218\u4e09\u56fd\u5173\u5361\u603b\u8868"
    ]
   }, 
   {
    "__tuple__": true, 
    "items": [
     "1e26e28e-d8f0-4fd7-8533-af4d6779fd0b", 
     "\u5f81\u6218\u4e09\u56fd\u5173\u5361\u4fe1\u606f\u8868"
    ]
   }
  ]
 }
]